claraw10/__init__.py
claraw10/clustering.py
claraw10/plotting.py
claraw10-0.0.1.dist-info/LICENSE
claraw10-0.0.1.dist-info/METADATA
claraw10-0.0.1.dist-info/WHEEL
claraw10-0.0.1.dist-info/top_level.txt
claraw10-0.0.1.dist-info/RECORD
