Metadata-Version: 2.1
Name: claraw10
Version: 0.0.1
Summary: A plotting and clustering package
Home-page: https://github.com/claradab/claraw10
Author: Clara
Author-email: clara@example.com
License: UNKNOWN
Platform: UNKNOWN
Classifier: Programming Language :: Python :: 3
Classifier: License :: OSI Approved :: MIT License
Classifier: Operating System :: OS Independent
Requires-Python: >=3.6
